cphec.py
cphec-1.0.dist-info/LICENSE
cphec-1.0.dist-info/METADATA
cphec-1.0.dist-info/WHEEL
cphec-1.0.dist-info/top_level.txt
cphec-1.0.dist-info/RECORD
