Metadata-Version: 2.1
Name: cphec
Version: 1.0
Summary: Check Point HEC API SDK
Home-page: https://github.com/travislockman/cp_hec_api_python_sdk
Author: Travis Lockman
License: Apache 2.0
License-File: LICENSE
Requires-Dist: requests
